eplaunch/__init__.py
eplaunch/__main__.py
eplaunch/configure.py
eplaunch/tk_runner.py
eplaunch/icons/icon.icns
eplaunch/icons/icon.ico
eplaunch/icons/icon.png
eplaunch/interface/__init__.py
eplaunch/interface/config.py
eplaunch/interface/dialog_external_viewers.py
eplaunch/interface/dialog_generic.py
eplaunch/interface/dialog_output.py
eplaunch/interface/dialog_weather.py
eplaunch/interface/dialog_workflow_dirs.py
eplaunch/interface/frame_main.py
eplaunch/interface/widget_dir_list.py
eplaunch/interface/widget_file_list.py
eplaunch/interface/widget_group_list.py
eplaunch/interface/resources/folder_closed.png
eplaunch/interface/resources/folder_opened.png
eplaunch/interface/resources/idf_editor_icon.png
eplaunch/utilities/__init__.py
eplaunch/utilities/cache.py
eplaunch/utilities/crossplatform.py
eplaunch/utilities/exceptions.py
eplaunch/utilities/version.py
eplaunch/workflows/__init__.py
eplaunch/workflows/base.py
eplaunch/workflows/manager.py
eplaunch/workflows/workflow.py
eplaunch/workflows/workflow_tester.py
eplaunch/workflows/workflow_thread.py
eplaunch/workflows/default/__init__.py
eplaunch/workflows/default/file_details.py
eplaunch/workflows/default/idf_details.py
eplaunch/workflows/default/site_location.py
energyplus_launch-3.7.2.dist-info/LICENSE
energyplus_launch-3.7.2.dist-info/METADATA
energyplus_launch-3.7.2.dist-info/WHEEL
energyplus_launch-3.7.2.dist-info/entry_points.txt
energyplus_launch-3.7.2.dist-info/top_level.txt
energyplus_launch-3.7.2.dist-info/RECORD
