Metadata-Version: 2.1
Name: energyplus-launch
Version: 3.7.2
Summary: Graphical Interface and Workflow Manager for EnergyPlus
Home-page: https://github.com/NREL/EP-Launch
Author: Jason Glazer and Edwin Lee for the United States Department of Energy
License: ModifiedBSD
Keywords: energyplus_launch,ep_launch,EnergyPlus,eplus,Energy+,Building Simulation,Whole Building Energy Simulation,Heat Transfer,HVAC,Modeling
Platform: Linux (Tested on Ubuntu)
Platform: MacOSX
Platform: Windows
Classifier: Development Status :: 4 - Beta
Classifier: Intended Audience :: Science/Research
Classifier: Natural Language :: English
Classifier: Operating System :: OS Independent
Classifier: Programming Language :: Python :: 3 :: Only
Classifier: Topic :: Scientific/Engineering
Classifier: Topic :: Scientific/Engineering :: Physics
Classifier: Topic :: Utilities
License-File: LICENSE
Requires-Dist: PLAN-Tools >=0.7
Requires-Dist: tkmacosx
